tomli_w/__init__.py
tomli_w/_writer.py
tomli_w/py.typed
tomli_w-0.4.0.dist-info/LICENSE
tomli_w-0.4.0.dist-info/WHEEL
tomli_w-0.4.0.dist-info/METADATA
tomli_w-0.4.0.dist-info/RECORD
